uranai/__init__.py
uranai/main.py
uranai-1.0.dist-info/METADATA
uranai-1.0.dist-info/WHEEL
uranai-1.0.dist-info/licenses/LICENSE
uranai-1.0.dist-info/RECORD
