Metadata-Version: 2.3
Name: uranai
Version: 1.0
Summary: 占いモジュール
Project-URL: Homepage, https://github.com/kota-41/uranai/
Project-URL: Issues, https://github.com/kota-41/uranai/issues
Author-email: こーた <info@onzhir.com>
License: MIT License
License-File: LICENSE
Classifier: License :: OSI Approved :: MIT License
Classifier: Operating System :: OS Independent
Classifier: Programming Language :: Python :: 3
Requires-Python: >=3.10.12
